xai_tabular_widget/__init__.py
xai_tabular_widget/_frontend.py
xai_tabular_widget/_version.py
xai_tabular_widget/tabular_widget.py
xai_tabular_widget/labextension/xai_tabular_widget-0.1.0.tgz
xai_tabular_widget/nbextension/__init__.py
xai_tabular_widget/nbextension/static/2fbd491f4f9c12ec3d0042f2a076d1e8.js
xai_tabular_widget/nbextension/static/50eef1f38f3cb3ec8ba0790285204ac9.js
xai_tabular_widget/nbextension/static/9f23c59f4bd79574a97e059c7750ca98.js
xai_tabular_widget/nbextension/static/d0350ae4da4bc9e8328a3c5725f240f5.js
xai_tabular_widget/nbextension/static/d532c229fa13b81f8b0abe869f119529.js
xai_tabular_widget/nbextension/static/extension.js
xai_tabular_widget/nbextension/static/index.js
xai_tabular_widget/nbextension/static/index.js.map
xai_tabular_widget/tests/__init__.py
xai_tabular_widget/tests/test_nbextension_path.py
xai_tabular_widget/tests/test_tabular_widget.py
xai_tabular_widget-0.1.0.data/data/etc/jupyter/nbconfig/notebook.d/xai_tabular_widget.json
xai_tabular_widget-0.1.0.data/data/share/jupyter/lab/extensions/xai_tabular_widget-0.1.0.tgz
xai_tabular_widget-0.1.0.data/data/share/jupyter/nbextensions/xai_tabular_widget/2fbd491f4f9c12ec3d0042f2a076d1e8.js
xai_tabular_widget-0.1.0.data/data/share/jupyter/nbextensions/xai_tabular_widget/50eef1f38f3cb3ec8ba0790285204ac9.js
xai_tabular_widget-0.1.0.data/data/share/jupyter/nbextensions/xai_tabular_widget/9f23c59f4bd79574a97e059c7750ca98.js
xai_tabular_widget-0.1.0.data/data/share/jupyter/nbextensions/xai_tabular_widget/d0350ae4da4bc9e8328a3c5725f240f5.js
xai_tabular_widget-0.1.0.data/data/share/jupyter/nbextensions/xai_tabular_widget/d532c229fa13b81f8b0abe869f119529.js
xai_tabular_widget-0.1.0.data/data/share/jupyter/nbextensions/xai_tabular_widget/extension.js
xai_tabular_widget-0.1.0.data/data/share/jupyter/nbextensions/xai_tabular_widget/index.js
xai_tabular_widget-0.1.0.data/data/share/jupyter/nbextensions/xai_tabular_widget/index.js.map
xai_tabular_widget-0.1.0.dist-info/LICENSE.txt
xai_tabular_widget-0.1.0.dist-info/METADATA
xai_tabular_widget-0.1.0.dist-info/WHEEL
xai_tabular_widget-0.1.0.dist-info/top_level.txt
xai_tabular_widget-0.1.0.dist-info/RECORD
